kalandra/__init__.py
kalandra/__main__.py
kalandra/auth/__init__.py
kalandra/auth/basic.py
kalandra/cli.py
kalandra/commands/update_mirror.py
kalandra/github_config_utils.py
kalandra/gitprotocol.py
kalandra/transports/__init__.py
kalandra/transports/base.py
kalandra/transports/file.py
kalandra/transports/http.py
kalandra/transports/ssh.py
kalandra-0.9.1.dist-info/WHEEL
kalandra-0.9.1.dist-info/entry_points.txt
kalandra-0.9.1.dist-info/METADATA
kalandra-0.9.1.dist-info/RECORD
