Metadata-Version: 2.3
Name: kalandra
Version: 0.9.1
Summary: 
Author: Lukasz Rekucki
Author-email: Lukasz Rekucki <lrekucki@gmail.com>
License: Apache-2.0
Requires-Dist: aiofiles>=25.1.0,<26.0.0
Requires-Dist: aiohttp>=3.13.3,<4.0.0
Requires-Dist: asyncssh>=2.22.0,<3.0.0
Requires-Dist: pygithub>=2.8.1,<3.0.0 ; extra == 'github'
Requires-Python: >=3.12
Provides-Extra: github
